scruf/__init__.py
scruf/compare.py
scruf/exception.py
scruf/execute.py
scruf/main.py
scruf/observe.py
scruf/parsers.py
scruf/runner.py
scruf/test.py
scruf/observers/__init__.py
scruf/observers/tap.py
scruf-0.4.1.data/scripts/scruf
scruf-0.4.1.dist-info/LICENSE
scruf-0.4.1.dist-info/METADATA
scruf-0.4.1.dist-info/WHEEL
scruf-0.4.1.dist-info/top_level.txt
scruf-0.4.1.dist-info/RECORD
